xclient/__init__.py
xclient/api/client/__init__.py
xclient/api/client/api/__init__.py
xclient/api/client/api/tasks/__init__.py
xclient/api/client/api/tasks/cancel_task.py
xclient/api/client/api/tasks/delete_task.py
xclient/api/client/api/tasks/get_task.py
xclient/api/client/api/tasks/list_tasks.py
xclient/api/client/api/tasks/submit_task.py
xclient/api/client/client.py
xclient/api/client/errors.py
xclient/api/client/models/__init__.py
xclient/api/client/models/error_response.py
xclient/api/client/models/message_response.py
xclient/api/client/models/task.py
xclient/api/client/models/task_alloc_tres_type_0.py
xclient/api/client/models/task_gres_detail_type_0_item.py
xclient/api/client/models/task_job_resources_type_0.py
xclient/api/client/models/task_list_response.py
xclient/api/client/models/task_resources_type_0.py
xclient/api/client/models/task_status.py
xclient/api/client/models/task_submit_request.py
xclient/api/client/models/task_submit_request_environment_type_0.py
xclient/api/client/models/task_submit_response.py
xclient/api/client/models/task_tres_type_0.py
xclient/api/client/models/task_tres_used_type_0.py
xclient/api/client/py.typed
xclient/api/client/types.py
xclient/connection_config.py
xclient/exceptions.py
xclient/task/__init__.py
xclient/task/client.py
xclient/task/task.py
xclient_python_sdk-0.0.2.dist-info/METADATA
xclient_python_sdk-0.0.2.dist-info/WHEEL
xclient_python_sdk-0.0.2.dist-info/RECORD
