Metadata-Version: 2.3
Name: xclient-python-sdk
Version: 0.0.2
Summary: XClient Python SDK for XCloud Service API
License: MIT
Author: xclient
Author-email: xclient@example.com
Requires-Python: >=3.9,<4.0
Classifier: License :: OSI Approved :: MIT License
Classifier: Programming Language :: Python :: 3
Classifier: Programming Language :: Python :: 3.9
Classifier: Programming Language :: Python :: 3.10
Classifier: Programming Language :: Python :: 3.11
Classifier: Programming Language :: Python :: 3.12
Classifier: Programming Language :: Python :: 3.13
Requires-Dist: attrs (>=23.2.0)
Requires-Dist: httpx (>=0.27.0,<1.0.0)
Requires-Dist: packaging (>=24.1)
Requires-Dist: python-dateutil (>=2.8.2)
Requires-Dist: typing-extensions (>=4.1.0)
Project-URL: Bug Tracker, https://github.com/xclient-service/xclient/issues
Project-URL: Homepage, https://xclient.cloud/
Project-URL: Repository, https://github.com/xcloud-service/xclient
